{"0": {"Nodo_S": 1, "Nodo_D": 0, "max_Lat": 21, "min_T": 45, "funcao": {"Nome": "Advanced Encryption Standard", "implementacao": {"nome": "AES4", "CLBs": 9561, "BRAM": 450, "DSPs": 0, "Lat": 7, "Throughput": 119.3}}, "valor": 41.928562298179806}, "1": {"Nodo_S": 2, "Nodo_D": 0, "max_Lat": 1558, "min_T": 102.6, "funcao": {"Nome": "Deep Packet Inspection", "implementacao": {"nome": "DPI5", "CLBs": 6048, "BRAM": 399, "DSPs": 0, "Lat": 1558, "Throughput": 102.6}}, "valor": 219.51690143175324}, "2": {"Nodo_S": 2, "Nodo_D": 0, "max_Lat": 278, "min_T": 0.8, "funcao": {"Nome": "Advanced Encryption Standard", "implementacao": {"nome": "AES4", "CLBs": 9561, "BRAM": 450, "DSPs": 0, "Lat": 7, "Throughput": 119.3}}, "valor": 163.17711828854652}, "3": {"Nodo_S": 0, "Nodo_D": 2, "max_Lat": 666, "min_T": 40, "funcao": {"Nome": "Deep Packet Inspection", "implementacao": {"nome": "DPI5", "CLBs": 6048, "BRAM": 399, "DSPs": 0, "Lat": 1558, "Throughput": 102.6}}, "valor": 184.87105931247723}, "4": {"Nodo_S": 0, "Nodo_D": 1, "max_Lat": 21, "min_T": 45, "funcao": {"Nome": "Deep Packet Inspection", "implementacao": {"nome": "DPI5", "CLBs": 6048, "BRAM": 399, "DSPs": 0, "Lat": 1558, "Throughput": 102.6}}, "valor": 37.594384669536694}}